pysheeter/PySheeter.py
pysheeter/__init__.py
pysheeter-1.0.6.dist-info/LICENSE
pysheeter-1.0.6.dist-info/METADATA
pysheeter-1.0.6.dist-info/WHEEL
pysheeter-1.0.6.dist-info/top_level.txt
pysheeter-1.0.6.dist-info/RECORD
