Metadata-Version: 2.1
Name: pysheeter
Version: 1.0.6
Summary: Lightweight Python-script to create sprite sheets from transparent PNGs with Pillow
Home-page: https://github.com/VictorWesterlund/pysheeter
Author: VicW
Author-email: victor.vesterlund@gmail.com
License: UNKNOWN
Platform: UNKNOWN
Classifier: Programming Language :: Python :: 3
Classifier: License :: OSI Approved :: MIT License
Classifier: Operating System :: OS Independent
Requires-Python: >=3.6
Requires-Dist: Pillow
